odoo/addons/sale_order_line_description_single_attribute/README.rst
odoo/addons/sale_order_line_description_single_attribute/__init__.py
odoo/addons/sale_order_line_description_single_attribute/__manifest__.py
odoo/addons/sale_order_line_description_single_attribute/i18n/es.po
odoo/addons/sale_order_line_description_single_attribute/i18n/it.po
odoo/addons/sale_order_line_description_single_attribute/i18n/sale_order_line_description_single_attribute.pot
odoo/addons/sale_order_line_description_single_attribute/models/__init__.py
odoo/addons/sale_order_line_description_single_attribute/models/product.py
odoo/addons/sale_order_line_description_single_attribute/readme/CONTRIBUTORS.rst
odoo/addons/sale_order_line_description_single_attribute/readme/DESCRIPTION.rst
odoo/addons/sale_order_line_description_single_attribute/readme/ROADMAP.rst
odoo/addons/sale_order_line_description_single_attribute/readme/USAGE.rst
odoo/addons/sale_order_line_description_single_attribute/static/description/icon.png
odoo/addons/sale_order_line_description_single_attribute/static/description/index.html
odoo/addons/sale_order_line_description_single_attribute/tests/__init__.py
odoo/addons/sale_order_line_description_single_attribute/tests/test_sale.py
odoo14_addon_sale_order_line_description_single_attribute-14.0.1.0.1.dev7.dist-info/METADATA
odoo14_addon_sale_order_line_description_single_attribute-14.0.1.0.1.dev7.dist-info/WHEEL
odoo14_addon_sale_order_line_description_single_attribute-14.0.1.0.1.dev7.dist-info/top_level.txt
odoo14_addon_sale_order_line_description_single_attribute-14.0.1.0.1.dev7.dist-info/RECORD
